xotless/_version.py
xotless/context.py
xotless/domains.py
xotless/enums.py
xotless/immutables.py
xotless/itertools.py
xotless/pickablenv.py
xotless/py.typed
xotless/ranges.py
xotless/release.py
xotless/release.pyi
xotless/tracing.py
xotless/trees.py
xotless/types.py
xotless/types.pyi
xotless/walk.py
xotless/testing/strategies/__init__.py
xotless/testing/strategies/domains.py
xotless-4.2.1.post2.dist-info/METADATA
xotless-4.2.1.post2.dist-info/WHEEL
xotless-4.2.1.post2.dist-info/RECORD
